mi_paquete/__init__.py
mi_paquete/mi_modulo.py
mi_paquete_gcardenas-0.3.dist-info/LICENSE
mi_paquete_gcardenas-0.3.dist-info/METADATA
mi_paquete_gcardenas-0.3.dist-info/WHEEL
mi_paquete_gcardenas-0.3.dist-info/top_level.txt
mi_paquete_gcardenas-0.3.dist-info/RECORD
