Metadata-Version: 2.1
Name: mi-paquete-gcardenas
Version: 0.3
Summary: Una breve descripción de tu paquete
Home-page: https://github.com/tu_usuario/mi_paquete
Author: Tu Nombre
Author-email: tu_email@example.com
License-File: LICENSE
